LICENSE
snakypy/imake/__init__.py
imake-0.3.1.dist-info/entry_points.txt
imake-0.3.1.dist-info/LICENSE
imake-0.3.1.dist-info/WHEEL
imake-0.3.1.dist-info/METADATA
imake-0.3.1.dist-info/RECORD
